pytest_gcs/__init__.py
pytest_gcs/storage/__init__.py
pytest_gcs/storage/ctyping.py
pytest_gcs/storage/logging_strings.py
pytest_gcs/storage/models.py
pytest_gcs/storage/plugin.py
pytest_google_cloud_storage-1.1.2.dist-info/licenses/LICENSE
pytest_google_cloud_storage-1.1.2.dist-info/METADATA
pytest_google_cloud_storage-1.1.2.dist-info/WHEEL
pytest_google_cloud_storage-1.1.2.dist-info/entry_points.txt
pytest_google_cloud_storage-1.1.2.dist-info/top_level.txt
pytest_google_cloud_storage-1.1.2.dist-info/RECORD
