Metadata-Version: 2.4
Name: pytest-google-cloud-storage
Version: 1.1.2
Summary: Pytest custom features, e.g. fixtures and various tests. Aimed to emulate Google Cloud Storage service
Author: Jankovn
Project-URL: Homepage, https://github.com/Jankovn/pytest-google-cloud-storage
Project-URL: Branches, https://github.com/Jankovn/pytest-google-cloud-storage/branches
Project-URL: Issues, https://github.com/Jankovn/pytest-google-cloud-storage/issues
Project-URL: PR, https://github.com/Jankovn/pytest-google-cloud-storage/pulls
Classifier: Intended Audience :: Developers
Classifier: Operating System :: MacOS
Classifier: Operating System :: Unix
Classifier: Programming Language :: Python :: 3 :: Only
Classifier: Programming Language :: Python :: 3.11
Classifier: Programming Language :: Python :: 3.12
Classifier: Programming Language :: Python :: 3.13
Classifier: Topic :: Software Development :: Libraries
Classifier: Topic :: Software Development :: Testing
Classifier: Topic :: Utilities
Classifier: Framework :: Pytest
Requires-Python: >=3.11
License-File: LICENSE
Requires-Dist: pytest>=8.0.0
Requires-Dist: pytest-cov>=6.0.0
Requires-Dist: docker>=7.0.0
Requires-Dist: pydantic>=2.11.0
Requires-Dist: pydantic-settings>=2.9.0
Requires-Dist: gcsfs>=2025.2.0
Requires-Dist: polars>=1.29.0
Dynamic: license-file
